setup.cfg
setup.py
Products/__init__.py
Products.ProxyIndex.egg-info/PKG-INFO
Products.ProxyIndex.egg-info/SOURCES.txt
Products.ProxyIndex.egg-info/dependency_links.txt
Products.ProxyIndex.egg-info/namespace_packages.txt
Products.ProxyIndex.egg-info/not-zip-safe
Products.ProxyIndex.egg-info/requires.txt
Products.ProxyIndex.egg-info/top_level.txt
Products/ProxyIndex/CREDITS.txt
Products/ProxyIndex/Expression.py
Products/ProxyIndex/HISTORY.txt
Products/ProxyIndex/INSTALL.txt
Products/ProxyIndex/LICENSE.txt
Products/ProxyIndex/ProxyIndex.py
Products/ProxyIndex/README.txt
Products/ProxyIndex/__init__.py
Products/ProxyIndex/homepage.html
Products/ProxyIndex/version.txt
Products/ProxyIndex/tests/__init__.py
Products/ProxyIndex/tests/testProxyIndex.py
Products/ProxyIndex/ui/ProxyIndexAddForm.dtml
Products/ProxyIndex/ui/ProxyIndexView.dtml
Products/ProxyIndex/www/index.gif