Metadata-Version: 1.0
Name: Products.ProxyIndex
Version: 1.2.3
Summary: Zope 2 catalog index which fetch its data using a TAL expression.
Home-page: http://infrae.com/products/silva
Author: Kapil Thangavel
Author-email: info@infrae.com
License: BSD and ZPL 2.0
Keywords: zope catalog proxy index
Platform: UNKNOWN
Classifier: Framework :: Zope2
Classifier: Programming Language :: Python
Classifier: Topic :: Software Development :: Libraries :: Python Modules
